pywe_base/__init__.py
pywe_base/base.py
pywe_base-1.0.9.dist-info/METADATA
pywe_base-1.0.9.dist-info/WHEEL
pywe_base-1.0.9.dist-info/top_level.txt
pywe_base-1.0.9.dist-info/RECORD
